qat/generators/hook_combinatorial_generators.so
qat/opt/__init__.so
qat/opt/binary_linear_integer_programming.so
qat/opt/boolexpr.so
qat/opt/circuit_generator.so
qat/opt/combinatorial_problem.so
qat/opt/dimacs.so
qat/opt/generators.so
qat/opt/graph_colouring.so
qat/opt/graph_partitioning.so
qat/opt/ising.so
qat/opt/job_generator.so
qat/opt/k_clique.so
qat/opt/max_cut.so
qat/opt/mixing_factory.so
qat/opt/mwis.so
qat/opt/np_prob_benchmarks.so
qat/opt/np_prob_benchmarks_annealers_examination.so
qat/opt/number_partitioning.so
qat/opt/qubo.so
qat/opt/qubo_ising_combprob_translators.so
qat/opt/results.so
qat/opt/schedule_generator.so
qat/opt/sqa_best_parameters.so
qat/opt/vertex_cover.so
qat/plugins/cost_function.so
qat/plugins/hook_vsolve.so
qat/vsolve/__init__.so
qat/vsolve/version.so
qat/vsolve/ansatz/__init__.so
qat/vsolve/ansatz/factory.so
qat/vsolve/ansatz/gray_synth.so
qat/vsolve/ansatz/helpers.so
qat/vsolve/optimize/__init__.so
qat/vsolve/optimize/pso.so
qat/vsolve/optimize/pso_algorithm.so
qat/vsolve/optimize/scipy_binder.so
qat/vsolve/optimize/spsa.so
qat/vsolve/optimize/spsa_algorithm.so
qat_variational-1.7.0.dist-info/licenses/LICENSE.txt
qat_variational-1.7.0.dist-info/METADATA
qat_variational-1.7.0.dist-info/WHEEL
qat_variational-1.7.0.dist-info/top_level.txt
qat_variational-1.7.0.dist-info/RECORD
